retakesearch/__init__.py
retakesearch/client.py
retakesearch/index.py
retakesearch/search.py
retakesearch_fork-0.2.0.dist-info/METADATA
retakesearch_fork-0.2.0.dist-info/WHEEL
retakesearch_fork-0.2.0.dist-info/RECORD
