Metadata-Version: 2.1
Name: retakesearch-fork
Version: 0.2.0
Summary: Python client for Retake: universal search infra for developers
Author: Ming Ying
Author-email: ming.ying.nyc@gmail.com
Requires-Python: >=3.6,<4
Classifier: Programming Language :: Python :: 3
Classifier: Programming Language :: Python :: 3.6
Classifier: Programming Language :: Python :: 3.7
Classifier: Programming Language :: Python :: 3.8
Classifier: Programming Language :: Python :: 3.9
Classifier: Programming Language :: Python :: 3.10
Classifier: Programming Language :: Python :: 3.11
Requires-Dist: certifi (>=2023.7.22,<2024.0.0)
Requires-Dist: retakesearch-py (>=2.2.2,<3.0.0)
